otripy/__init__.py
otripy/config.py
otripy/icon_picker.py
otripy/journey.py
otripy/limited_color_picker.py
otripy/location.py
otripy/location_list_view.py
otripy/main.py
otripy/nextcloud.py
otripy/nextcloud_uuid.py
otripy/nextcloud_with_api.py
otripy/note_widget.py
otripy/rename_popup.py
otripy/search_popup.py
otripy/toolbar.py
otripy/resources/__init__.py
otripy/resources/icons/0.svg
otripy/resources/icons/1.svg
otripy/resources/icons/2.svg
otripy/resources/icons/3.svg
otripy/resources/icons/4.svg
otripy/resources/icons/5.svg
otripy/resources/icons/6.svg
otripy/resources/icons/7.svg
otripy/resources/icons/8.svg
otripy/resources/icons/9.svg
otripy/resources/icons/__init__.py
otripy/resources/icons/a.svg
otripy/resources/icons/address-book.svg
otripy/resources/icons/address-card.svg
otripy/resources/icons/align-center.svg
otripy/resources/icons/align-justify.svg
otripy/resources/icons/align-left.svg
otripy/resources/icons/align-right.svg
otripy/resources/icons/anchor-circle-check.svg
otripy/resources/icons/anchor-circle-exclamation.svg
otripy/resources/icons/anchor-circle-xmark.svg
otripy/resources/icons/anchor-lock.svg
otripy/resources/icons/anchor.svg
otripy/resources/icons/angle-down.svg
otripy/resources/icons/angle-left.svg
otripy/resources/icons/angle-right.svg
otripy/resources/icons/angle-up.svg
otripy/resources/icons/angles-down.svg
otripy/resources/icons/angles-left.svg
otripy/resources/icons/angles-right.svg
otripy/resources/icons/angles-up.svg
otripy/resources/icons/ankh.svg
otripy/resources/icons/apple-whole.svg
otripy/resources/icons/archway.svg
otripy/resources/icons/arrow-down-1-9.svg
otripy/resources/icons/arrow-down-9-1.svg
otripy/resources/icons/arrow-down-a-z.svg
otripy/resources/icons/arrow-down-long.svg
otripy/resources/icons/arrow-down-short-wide.svg
otripy/resources/icons/arrow-down-up-across-line.svg
otripy/resources/icons/arrow-down-up-lock.svg
otripy/resources/icons/arrow-down-wide-short.svg
otripy/resources/icons/arrow-down-z-a.svg
otripy-1.2.3.dist-info/METADATA
otripy-1.2.3.dist-info/WHEEL
otripy-1.2.3.dist-info/entry_points.txt
otripy-1.2.3.dist-info/RECORD
