Metadata-Version: 2.4
Name: otripy
Version: 1.2.3
Summary: A tool to plan your next trip
Project-URL: Homepage, https://github.com/kleag/otripy
Project-URL: Repository, https://github.com/kleag/otripy
Project-URL: Issues, https://github.com/kleag/otripy/issues
Author-email: "Gaël de Chalendar (aka Kleag)" <kleagg@gmail.com>
License: AGPL
Keywords: journey,map,openstreetmap,planning,tourism,trip
Classifier: Development Status :: 5 - Production/Stable
Classifier: Intended Audience :: End Users/Desktop
Classifier: License :: OSI Approved :: GNU Affero General Public License v3
Classifier: Natural Language :: English
Classifier: Operating System :: MacOS
Classifier: Operating System :: Microsoft :: Windows
Classifier: Operating System :: POSIX :: Linux
Classifier: Operating System :: Unix
Classifier: Programming Language :: Python :: 3
Classifier: Programming Language :: Python :: 3.10
Classifier: Programming Language :: Python :: 3.11
Classifier: Programming Language :: Python :: 3.12
Classifier: Programming Language :: Python :: 3.13
Requires-Python: >=3.10
Requires-Dist: folium>=0.19.5
Requires-Dist: geopy>=2.4.1
Requires-Dist: lxml>=5.3.1
Requires-Dist: markdown>=3.7
Requires-Dist: nc-py-api>=0.19.0
Requires-Dist: numpy>=2.2.3
Requires-Dist: packaging>=24.2
Requires-Dist: pillow>=11.1.0
Requires-Dist: pyside6>=6.8.2.1
Requires-Dist: typing-extensions>=4.12.2
Provides-Extra: build
Requires-Dist: bumpver; extra == 'build'
Provides-Extra: deploy
Requires-Dist: uv; extra == 'deploy'
Provides-Extra: dev
Requires-Dist: black; extra == 'dev'
Requires-Dist: mypy; extra == 'dev'
Requires-Dist: pytest; extra == 'dev'
Requires-Dist: ruff; extra == 'dev'
